README.md
setup.py
doorstopnew/__init__.py
doorstopnew/common.py
doorstopnew/settings.py
doorstopnew/cli/__init__.py
doorstopnew/cli/commands.py
doorstopnew/cli/main.py
doorstopnew/cli/utilities.py
doorstopnew/core/__init__.py
doorstopnew/core/base.py
doorstopnew/core/builder.py
doorstopnew/core/document.py
doorstopnew/core/editor.py
doorstopnew/core/exporter.py
doorstopnew/core/importer.py
doorstopnew/core/item.py
doorstopnew/core/publisher.py
doorstopnew/core/tree.py
doorstopnew/core/types.py
doorstopnew/core/vcs/__init__.py
doorstopnew/core/vcs/base.py
doorstopnew/core/vcs/git.py
doorstopnew/core/vcs/mercurial.py
doorstopnew/core/vcs/mockvcs.py
doorstopnew/core/vcs/subversion.py
doorstopnew/core/vcs/veracity.py
doorstopnew/server/__init__.py
doorstopnew/server/client.py
doorstopnew/server/main.py
doorstopnew/server/utilities.py
doorstopnewtwo.egg-info/PKG-INFO
doorstopnewtwo.egg-info/SOURCES.txt
doorstopnewtwo.egg-info/dependency_links.txt
doorstopnewtwo.egg-info/top_level.txt